tests/__init__.py
tests/settings.py
tests/tests.py
wrapwith/__init__.py
wrapwith/templatetags/__init__.py
wrapwith/templatetags/wrapwith.py
django_wrapwith-0.0.2.dist-info/LICENSE
django_wrapwith-0.0.2.dist-info/METADATA
django_wrapwith-0.0.2.dist-info/WHEEL
django_wrapwith-0.0.2.dist-info/top_level.txt
django_wrapwith-0.0.2.dist-info/RECORD
