Metadata-Version: 2.1
Name: django-wrapwith
Version: 0.0.2
Summary: A Django template tag for wrapping a template block in a reusable enclosing template
Home-page: https://github.com/dabapps/django-wrapwith
Author: Jamie Matthews
Author-email: jamie@dabapps.com
License: UNKNOWN
Platform: UNKNOWN
Classifier: Topic :: Internet :: WWW/HTTP
Classifier: Environment :: Web Environment
Classifier: Programming Language :: Python :: 3
Classifier: License :: OSI Approved :: BSD License
Classifier: Framework :: Django
Classifier: Operating System :: OS Independent
